BHClustering/__init__.py
BHClustering/__version__.py
BHClustering/functions.py
BHClustering-0.0.3.dist-info/DESCRIPTION.rst
BHClustering-0.0.3.dist-info/METADATA
BHClustering-0.0.3.dist-info/RECORD
BHClustering-0.0.3.dist-info/WHEEL
BHClustering-0.0.3.dist-info/metadata.json
BHClustering-0.0.3.dist-info/top_level.txt
