Metadata-Version: 2.0
Name: BHClustering
Version: 0.0.3
Summary: Bayesian Hierarchical Clustering
Home-page: https://github.com/xiyanghu/BHC
Author: Xiyang Hu, Shuangjie Zhang
Author-email: xiyanghu@outlook.com
License: MIT
Platform: UNKNOWN
Classifier: License :: OSI Approved :: MIT License
Classifier: Programming Language :: Python
Classifier: Programming Language :: Python :: 3
Classifier: Programming Language :: Python :: 3.6
Classifier: Programming Language :: Python :: Implementation :: CPython
Classifier: Programming Language :: Python :: Implementation :: PyPy
Requires-Python: >=3.6.0
